COPYING
MANIFEST.in
README
setup.py
./__init__.py
./health_who_essential_medicines.py
./tryton.cfg
./data/WHO_list_of_essential_medicines.xml
./data/WHO_products.xml
./data/medicament_categories.xml
./doc/index.rst
./locale/ar.po
./locale/de.po
./locale/el.po
./locale/es.po
./locale/fr.po
./locale/it_IT.po
./locale/ja_JP.po
./locale/lo.po
./locale/pt_BR.po
./locale/zh_CN.po
./tests/__init__.py
./tests/test_health_who_essential_medicines.py
data/WHO_list_of_essential_medicines.xml
data/WHO_products.xml
data/medicament_categories.xml
locale/ar.po
locale/de.po
locale/el.po
locale/es.po
locale/fr.po
locale/it_IT.po
locale/ja_JP.po
locale/lo.po
locale/pt_BR.po
locale/zh_CN.po
trytond_health_who_essential_medicines.egg-info/PKG-INFO
trytond_health_who_essential_medicines.egg-info/SOURCES.txt
trytond_health_who_essential_medicines.egg-info/dependency_links.txt
trytond_health_who_essential_medicines.egg-info/entry_points.txt
trytond_health_who_essential_medicines.egg-info/not-zip-safe
trytond_health_who_essential_medicines.egg-info/requires.txt
trytond_health_who_essential_medicines.egg-info/top_level.txt